NiukeKuaixiaoXingyeQiuzhiGonglveBaiweiPian20212022Fix1/README.md
NiukeKuaixiaoXingyeQiuzhiGonglveBaiweiPian20212022Fix1/__init__.py
NiukeKuaixiaoXingyeQiuzhiGonglveBaiweiPian20212022Fix1/__main__.py
NiukeKuaixiaoXingyeQiuzhiGonglveBaiweiPian20212022Fix1/file.epub
NiukeKuaixiaoXingyeQiuzhiGonglveBaiweiPian20212022Fix1/index.html
NiukeKuaixiaoXingyeQiuzhiGonglveBaiweiPian20212022Fix1/css/__init__.py
NiukeKuaixiaoXingyeQiuzhiGonglveBaiweiPian20212022Fix1/css/annotations.css
NiukeKuaixiaoXingyeQiuzhiGonglveBaiweiPian20212022Fix1/css/main.css
NiukeKuaixiaoXingyeQiuzhiGonglveBaiweiPian20212022Fix1/css/normalize.css
NiukeKuaixiaoXingyeQiuzhiGonglveBaiweiPian20212022Fix1/css/popup.css
NiukeKuaixiaoXingyeQiuzhiGonglveBaiweiPian20212022Fix1/font/__init__.py
NiukeKuaixiaoXingyeQiuzhiGonglveBaiweiPian20212022Fix1/font/fontello.eot
NiukeKuaixiaoXingyeQiuzhiGonglveBaiweiPian20212022Fix1/font/fontello.svg
NiukeKuaixiaoXingyeQiuzhiGonglveBaiweiPian20212022Fix1/font/fontello.ttf
NiukeKuaixiaoXingyeQiuzhiGonglveBaiweiPian20212022Fix1/font/fontello.woff
NiukeKuaixiaoXingyeQiuzhiGonglveBaiweiPian20212022Fix1/img/__init__.py
NiukeKuaixiaoXingyeQiuzhiGonglveBaiweiPian20212022Fix1/img/annotator-glyph-sprite.png
NiukeKuaixiaoXingyeQiuzhiGonglveBaiweiPian20212022Fix1/img/annotator-icon-sprite.png
NiukeKuaixiaoXingyeQiuzhiGonglveBaiweiPian20212022Fix1/img/apple-touch-icon.png
NiukeKuaixiaoXingyeQiuzhiGonglveBaiweiPian20212022Fix1/img/cancelfullscreen.png
NiukeKuaixiaoXingyeQiuzhiGonglveBaiweiPian20212022Fix1/img/close.png
NiukeKuaixiaoXingyeQiuzhiGonglveBaiweiPian20212022Fix1/img/fullscreen.png
NiukeKuaixiaoXingyeQiuzhiGonglveBaiweiPian20212022Fix1/img/loader.gif
NiukeKuaixiaoXingyeQiuzhiGonglveBaiweiPian20212022Fix1/img/menu-icon.png
NiukeKuaixiaoXingyeQiuzhiGonglveBaiweiPian20212022Fix1/img/save.png
NiukeKuaixiaoXingyeQiuzhiGonglveBaiweiPian20212022Fix1/img/saved.png
NiukeKuaixiaoXingyeQiuzhiGonglveBaiweiPian20212022Fix1/img/settings-s.png
niuke_kuaixiao_xingye_qiuzhi_gonglve_baiwei_pian_2021_2022_fix1-2025.3.25.0.dist-info/METADATA
niuke_kuaixiao_xingye_qiuzhi_gonglve_baiwei_pian_2021_2022_fix1-2025.3.25.0.dist-info/WHEEL
niuke_kuaixiao_xingye_qiuzhi_gonglve_baiwei_pian_2021_2022_fix1-2025.3.25.0.dist-info/entry_points.txt
niuke_kuaixiao_xingye_qiuzhi_gonglve_baiwei_pian_2021_2022_fix1-2025.3.25.0.dist-info/top_level.txt
niuke_kuaixiao_xingye_qiuzhi_gonglve_baiwei_pian_2021_2022_fix1-2025.3.25.0.dist-info/RECORD
